Workbook

Sheet Dashboard
B2: Azure OpenAI PTU Calculator
B3: Enterprise Capacity Planning Framework
B4: Version 1.0 | Deloitte Microsoft Practice
B6: EXECUTIVE SUMMARY
B7: Metric | C7: Value | D7: Unit | E7: Status
B8: Total PTUs Required | C8: ='Capacity Summary'!D15 | D8: PTUs | E8: =IF(C8>0,"✓ Calculated","⚠ Enter Data")
B9: Total Monthly Cost (Hourly) | C9: ='Cost Analysis'!D8 | D9: USD | E9: =IF(C9>0,"✓ Calculated","-")
B10: Total Monthly Cost (Reserved) | C10: ='Cost Analysis'!D12 | D10: USD | E10: =IF(C10>0,"✓ Calculated","-")
B11: Annual Savings with Reservation | C11: ='Cost Analysis'!D16 | D11: USD | E11: =IF(C11>0,"✓ Calculated","-")
B12: Applications Configured | C12: =COUNTA('Workload Inputs'!B8:B27)-COUNTBLANK('Workload Inputs'!B8:B27) | D12: Apps | E12: =IF(C12>0,"✓ Ready","⚠ Configure")
B13: PTU Utilization Target | C13: =Configuration!C12 | D13: % | E13: =IF(C13>0,"✓ Set","⚠ Set Target")
B16: QUICK NAVIGATION
B17: 1. Configuration | C17: Set global parameters and rates
B18: 2. Workload Inputs | C18: Enter application requirements
B19: 3. PTU Rates | C19: Model-specific conversion rates
B20: 4. Capacity Summary | C20: View PTU calculations
B21: 5. Cost Analysis | C21: Compare PTU vs PAYGO costs
B22: 6. Spillover Planner | C22: Configure overflow strategy
B23: 7. Reservation Optimizer | C23: Plan commitment terms
B24: 8. Chargeback Model | C24: Allocate costs by application
B27: INSTRUCTIONS
B28: 1. Start with the Configuration sheet to set your pricing region and buffer percentages
B29: 2. Enter your workload details in the Workload Inputs sheet (blue cells are inputs)
B30: 3. Review PTU Rates and update if Microsoft has published new rates
B31: 4. Check Capacity Summary for calculated PTU requirements
B32: 5. Use Cost Analysis to compare economic scenarios
B33: 6. Configure Spillover Planner for hybrid PTU/PAYGO architecture

Sheet Configuration
B2: Global Configuration
B4: PRICING & REGION SETTINGS
B5: Parameter | C5: Value | D5: Description
B6: Deployment Type | C6: Global Provisioned | D6: Options: Global Provisioned, Data Zone Provisioned, Regional Provisioned
B7: Primary Region | C7: East US 2 | D7: Azure region for primary deployment
B8: Secondary Region | C8: West US 2 | D8: Azure region for failover/spillover
B9: Currency | C9: USD | D9: Pricing currency
B10: Hourly PTU Rate ($/PTU/hr) | C10: 0.0396 | D10: Current rate from Azure pricing calculator
B11: 1-Year Reservation Discount | C11: 0.2 | D11: Discount percentage for annual commitment
B12: 3-Year Reservation Discount | C12: 0.4 | D12: Discount percentage for 3-year commitment
B15: CAPACITY PLANNING PARAMETERS
B16: Parameter | C16: Value | D16: Description
B17: Target PTU Utilization % | C17: 0.85 | D17: Target utilization before spillover (0.80-0.95 recommended)
B18: Buffer Percentage | C18: 0.15 | D18: Additional capacity buffer for variance
B19: Peak Traffic Multiplier | C19: 1.2 | D19: Multiplier for expected peak vs average
B20: Hours per Month | C20: 730 | D20: Standard hours for monthly calculations
B23: PAYGO COMPARISON RATES (per 1M tokens)
B24: Model/Type | C24: Rate ($) | D24: Description
B25: GPT-4o Input | C25: 2.5 | D25: PAYGO rate per 1M input tokens
B26: GPT-4o Output | C26: 10 | D26: PAYGO rate per 1M output tokens
B27: GPT-4 Turbo Input | C27: 10 | D27: PAYGO rate per 1M input tokens
B28: GPT-4 Turbo Output | C28: 30 | D28: PAYGO rate per 1M output tokens
B29: GPT-3.5 Turbo Input | C29: 0.5 | D29: PAYGO rate per 1M input tokens
B30: GPT-3.5 Turbo Output | C30: 1.5 | D30: PAYGO rate per 1M output tokens
B31: gpt-4.1 Input | C31: 2 | D31: PAYGO rate per 1M input tokens
B32: gpt-4.1 Output | C32: 8 | D32: PAYGO rate per 1M output tokens
B33: gpt-4.1-mini Input | C33: 0.4 | D33: PAYGO rate per 1M input tokens
B34: gpt-4.1-mini Output | C34: 1.6 | D34: PAYGO rate per 1M output tokens
B35: gpt-5 Input | C35: 5 | D35: PAYGO rate per 1M input tokens
B36: gpt-5 Output | C36: 15 | D36: PAYGO rate per 1M output tokens
... B38: DeepSeek-R1 Output | C38: 2.19 | D38: PAYGO rate per 1M output tokens

Sheet Workload Inputs
B2: Workload Input Configuration
B3: Enter your application workload details below. Blue cells are inputs.
B5: APPLICATION WORKLOADS
B7: Application Name | C7: Model | D7: Avg Input Tokens | E7: Avg Output Tokens | F7: Peak RPM | G7: Daily Hours | H7: Priority (1-3) | I7: Notes
B8: Customer Chatbot | C8: GPT-4o | D8: 800 | E8: 400 | F8: 100 | G8: 16 | H8: 1 | I8: Production chatbot
B9: Internal Copilot | C9: GPT-4o | D9: 1200 | E9: 600 | F9: 50 | G9: 10 | H9: 2 | I9: Employee assistant
B10: Document Summarizer | C10: GPT-4 Turbo | D10: 4000 | E10: 1000 | F10: 20 | G10: 8 | H10: 2 | I10: Legal docs
B11: Code Assistant | C11: GPT-4o | D11: 2000 | E11: 1500 | F11: 30 | G11: 12 | H11: 1 | I11: Dev team
B30: CALCULATED METRICS (Do not edit)
B31: Application | C31: Input TPM | D31: Output TPM | E31: Total TPM | F31: Est. PTUs
B32: =B8 | C32: =IF(B8<>"",D8*F8,"") | D32: =IF(B8<>"",E8*F8,"") | E32: =IF(B8<>"",C32+D32,"") | F32: =IF(B8<>"",IFERROR(E32/'PTU Rates'!$C$7,0),"")
B33: =B9 | C33: =IF(B9<>"",D9*F9,"") | D33: =IF(B9<>"",E9*F9,"") | E33: =IF(B9<>"",C33+D33,"") | F33: =IF(B9<>"",IFERROR(E33/'PTU Rates'!$C$7,0),"")
B34: =B10 | C34: =IF(B10<>"",D10*F10,"") | D34: =IF(B10<>"",E10*F10,"") | E34: =IF(B10<>"",C34+D34,"") | F34: =IF(B10<>"",IFERROR(E34/'PTU Rates'!$C$7,0),"")
B35: =B11 | C35: =IF(B11<>"",D11*F11,"") | D35: =IF(B11<>"",E11*F11,"") | E35: =IF(B11<>"",C35+D35,"") | F35: =IF(B11<>"",IFERROR(E35/'PTU Rates'!$C$7,0),"")
B36: =B12 | C36: =IF(B12<>"",D12*F12,"") | D36: =IF(B12<>"",E12*F12,"") | E36: =IF(B12<>"",C36+D36,"") | F36: =IF(B12<>"",IFERROR(E36/'PTU Rates'!$C$7,0),"")
B37: =B13 | C37: =IF(B13<>"",D13*F13,"") | D37: =IF(B13<>"",E13*F13,"") | E37: =IF(B13<>"",C37+D37,"") | F37: =IF(B13<>"",IFERROR(E37/'PTU Rates'!$C$7,0),"")
B38: =B14 | C38: =IF(B14<>"",D14*F14,"") | D38: =IF(B14<>"",E14*F14,"") | E38: =IF(B14<>"",C38+D38,"") | F38: =IF(B14<>"",IFERROR(E38/'PTU Rates'!$C$7,0),"")
B39: =B15 | C39: =IF(B15<>"",D15*F15,"") | D39: =IF(B15<>"",E15*F15,"") | E39: =IF(B15<>"",C39+D39,"") | F39: =IF(B15<>"",IFERROR(E39/'PTU Rates'!$C$7,0),"")
B40: =B16 | C40: =IF(B16<>"",D16*F16,"") | D40: =IF(B16<>"",E16*F16,"") | E40: =IF(B16<>"",C40+D40,"") | F40: =IF(B16<>"",IFERROR(E40/'PTU Rates'!$C$7,0),"")
B41: =B17 | C41: =IF(B17<>"",D17*F17,"") | D41: =IF(B17<>"",E17*F17,"") | E41: =IF(B17<>"",C41+D41,"") | F41: =IF(B17<>"",IFERROR(E41/'PTU Rates'!$C$7,0),"")
B42: =B18 | C42: =IF(B18<>"",D18*F18,"") | D42: =IF(B18<>"",E18*F18,"") | E42: =IF(B18<>"",C42+D42,"") | F42: =IF(B18<>"",IFERROR(E42/'PTU Rates'!$C$7,0),"")
B43: =B19 | C43: =IF(B19<>"",D19*F19,"") | D43: =IF(B19<>"",E19*F19,"") | E43: =IF(B19<>"",C43+D43,"") | F43: =IF(B19<>"",IFERROR(E43/'PTU Rates'!$C$7,0),"")
... B51: =B27 | C51: =IF(B27<>"",D27*F27,"") | D51: =IF(B27<>"",E27*F27,"") | E51: =IF(B27<>"",C51+D51,"") | F51: =IF(B27<>"",IFERROR(E51/'PTU Rates'!$C$7,0),"")
B53: TOTALS | C53: =SUMIF(C32:C51,">0") | D53: =SUMIF(D32:D51,">0") | E53: =SUMIF(E32:E51,">0") | F53: =SUMIF(F32:F51,">0")

Sheet PTU Rates
B2: PTU Conversion Rates
B3: Update these rates quarterly from Microsoft's official calculator
B5: MODEL-SPECIFIC RATES
B6: Model | C6: TPM per PTU (Combined) | D6: Input TPM/PTU | E6: Output TPM/PTU | F6: Last Updated | G6: Output Ratio
B7: gpt-5.2 | C7: 3400 | D7: 3400 | E7: 425 | F7: Feb 2026 | G7: 8:1
B8: gpt-5 | C8: 4750 | D8: 4750 | E8: 594 | F8: Feb 2026 | G8: 8:1
B9: gpt-5-mini | C9: 23750 | D9: 23750 | E9: 2969 | F9: Feb 2026 | G9: 8:1
B10: gpt-4.1 | C10: 3000 | D10: 3000 | E10: 750 | F10: Feb 2026 | G10: 4:1
B11: gpt-4.1-mini | C11: 14900 | D11: 14900 | E11: 3725 | F11: Feb 2026 | G11: 4:1
B12: gpt-4.1-nano | C12: 59400 | D12: 59400 | E12: 14850 | F12: Feb 2026 | G12: 4:1
B13: GPT-4o | C13: 2500 | D13: 2500 | E13: 833 | F13: Feb 2026 | G13: separate
B14: GPT-4o-mini | C14: 37000 | D14: 37000 | E14: 12333 | F14: Feb 2026 | G14: separate
B15: GPT-4 Turbo | C15: 1200 | D15: 1200 | E15: 400 | F15: Feb 2026 | G15: legacy
B16: GPT-4 | C16: 800 | D16: 800 | E16: 267 | F16: Feb 2026 | G16: legacy
B17: GPT-3.5 Turbo | C17: 10000 | D17: 10000 | E17: 3333 | F17: Feb 2026 | G17: legacy
B18: o1 | C18: 500 | D18: 500 | E18: 167 | F18: Feb 2026 | G18: separate
... B22: o4-mini | C22: 1800 | D22: 1800 | E22: 225 | F22: Feb 2026 | G22: 8:1
G23: 4:1
B26: MINIMUM PTU INCREMENTS | C26: 50 | D26: 50 | E26: Higher minimum, regional data residency
B27: Deployment Type | C27: Minimum PTUs | D27: Increment Size | E27: Notes
B28: Global Provisioned | C28: 15 | D28: 5 | E28: Lowest minimum for cost-effective testing
C29: 50 | D29: 50 | E29: Higher minimum, regional data residency
C30: 100 | D30: 100 | E30: Highest minimum, strict data sovereignty
B32: RATE CALCULATION NOTES
B33: • For gpt-5/o3/o4 series: 1 output token = 8 input tokens (8:1 ratio)
B34: • For gpt-4.1 series: 1 output token = 4 input tokens (4:1 ratio)
B35: • For GPT-4o/o1: Input and Output TPM calculated separately
B36: • Legacy models (GPT-4, GPT-3.5): Use combined TPM calculation
B37: • Always validate against: https://oai.azure.com/portal/calculator
B38: • Rates verified from Microsoft docs - Feb 2026

Sheet Capacity Summary
B2: PTU Capacity Summary
B4: CAPACITY CALCULATION
B5: Metric | C5: Value | D5: Unit | E5: Notes
B6: Total Input TPM | C6: ='Workload Inputs'!C53 | D6: tokens/min | E6: Sum of all application input TPM
B7: Total Output TPM | C7: ='Workload Inputs'!D53 | D7: tokens/min | E7: Sum of all application output TPM
B8: Total Combined TPM | C8: ='Workload Inputs'!E53 | D8: tokens/min | E8: Total throughput requirement
B9: Base PTU Requirement | C9: ='Workload Inputs'!F53 | D9: PTUs | E9: Raw calculation before adjustments
B10: Buffer Allocation | C10: =D8*Configuration!C18 | D10: PTUs | E10: Additional capacity for variance
B11: Peak Traffic Adjustment | C11: =D8*Configuration!C19 | D11: PTUs | E11: Capacity for peak periods
B13: Subtotal PTUs | C13: =D8+D9+D10 | D13: PTUs | E13: Total before rounding
B14: Minimum Increment | C14: ='PTU Rates'!C18 | D14: PTUs | E14: Based on deployment type
B16: TOTAL PTUs REQUIRED | C16: =CEILING(D12,D13) | D16: PTUs | E16: Final rounded PTU requirement
B20: UTILIZATION PROJECTIONS
B21: Scenario | C21: PTUs Deployed | D21: Expected Utilization | E21: Spillover % | F21: Monthly Hours
B22: Conservative (100% PTU) | C22: =D15 | D22: =Configuration!C17 | E22: 0% | F22: 730
B23: Balanced (90% PTU) | C23: =ROUND(D15*0.9,0) | D23: =Configuration!C17/0.9 | E23: 10% | F23: 730
B24: Aggressive (80% PTU) | C24: =ROUND(D15*0.8,0) | D24: =Configuration!C17/0.8 | E24: 20% | F24: 730

Sheet Cost Analysis
B2: Cost Analysis & Comparison
B4: PTU COST CALCULATIONS
B5: Metric | C5: Value | D5: Unit
B6: PTUs Required | C6: ='Capacity Summary'!D15 | D6: PTUs
B7: Hourly Rate | C7: =Configuration!C10 | D7: $/PTU/hr
B9: Monthly Cost (Hourly Billing) | C9: =D5*D6*730 | D9: USD
B10: Annual Cost (Hourly Billing) | C10: =D8*12 | D10: USD
B12: 1-Year Reserved Monthly | C12: =D8*(1-Configuration!C11) | D12: USD
B13: 1-Year Reserved Annual | C13: =D12*12 | D13: USD
B15: 3-Year Reserved Monthly | C15: =D8*(1-Configuration!C12) | D15: USD
B16: 3-Year Reserved Annual | C16: =D15*12 | D16: USD
B18: Annual Savings (1-Year) | C18: =D9-D13 | D18: USD
B19: Annual Savings (3-Year) | C19: =D9-D16 | D19: USD
B23: PAYGO COMPARISON
B24: Metric | C24: Value | D24: Unit
B25: Total Monthly Tokens (Input) | C25: ='Workload Inputs'!C53*Configuration!C20*60 | D25: tokens
B26: Total Monthly Tokens (Output) | C26: ='Workload Inputs'!D53*Configuration!C20*60 | D26: tokens
B28: PAYGO Input Cost | C28: =D24/1000000*Configuration!C25 | D28: USD
B29: PAYGO Output Cost | C29: =D25/1000000*Configuration!C26 | D29: USD
B30: Total PAYGO Monthly Cost | C30: =D28+D29 | D30: USD
B32: PTU vs PAYGO Difference | C32: =D8-D30 | D32: USD
B33: PTU Savings % | C33: =IF(D30>0,(D30-D8)/D30,0) | D33: %
B37: BREAK-EVEN ANALYSIS
B38: Break-even TPM (Hourly) | C38: =D8/((Configuration!C25+Configuration!C26)/2)*1000000/Configuration!C20/60 | D38: TPM

Sheet Spillover Planner
B2: Spillover Strategy Planner
B3: Configure hybrid PTU + PAYGO architecture for cost optimization
B5: SPILLOVER CONFIGURATION
B6: Parameter | C6: Value | D6: Description
B7: Base PTU Allocation % | C7: 0.85 | D7: Portion of peak traffic handled by PTU
B8: Expected Spillover % | C8: 0.15 | D8: Traffic expected to overflow to PAYGO
B9: Spillover Latency Tolerance | C9: Acceptable | D9: Options: Low, Acceptable, High
B12: SPILLOVER COST SCENARIOS
B13: Scenario | C13: PTU % | D13: PTUs | E13: PTU Cost | F13: Spillover Cost | G13: Total Cost | H13: vs 100% PTU
B14: 100% PTU (No Spillover) | C14: 1 | D14: =CEILING('Capacity Summary'!D15*C14,'PTU Rates'!C18) | E14: =D14*Configuration!C10*730 | F14: =(1-C14)*'Cost Analysis'!D30 | G14: =E14+F14 | H14: =G14-$G$14
B15: 95% PTU / 5% Spillover | C15: 0.95 | D15: =CEILING('Capacity Summary'!D15*C15,'PTU Rates'!C18) | E15: =D15*Configuration!C10*730 | F15: =(1-C15)*'Cost Analysis'!D30 | G15: =E15+F15 | H15: =G15-$G$14
B16: 90% PTU / 10% Spillover | C16: 0.9 | D16: =CEILING('Capacity Summary'!D15*C16,'PTU Rates'!C18) | E16: =D16*Configuration!C10*730 | F16: =(1-C16)*'Cost Analysis'!D30 | G16: =E16+F16 | H16: =G16-$G$14
B17: 85% PTU / 15% Spillover | C17: 0.85 | D17: =CEILING('Capacity Summary'!D15*C17,'PTU Rates'!C18) | E17: =D17*Configuration!C10*730 | F17: =(1-C17)*'Cost Analysis'!D30 | G17: =E17+F17 | H17: =G17-$G$14
B18: 80% PTU / 20% Spillover | C18: 0.8 | D18: =CEILING('Capacity Summary'!D15*C18,'PTU Rates'!C18) | E18: =D18*Configuration!C10*730 | F18: =(1-C18)*'Cost Analysis'!D30 | G18: =E18+F18 | H18: =G18-$G$14
B19: 75% PTU / 25% Spillover | C19: 0.75 | D19: =CEILING('Capacity Summary'!D15*C19,'PTU Rates'!C18) | E19: =D19*Configuration!C10*730 | F19: =(1-C19)*'Cost Analysis'!D30 | G19: =E19+F19 | H19: =G19-$G$14
B22: RECOMMENDATION
B23: Optimal Spillover Configuration: | C23: =INDEX(B14:B19,MATCH(MIN(G14:G19),G14:G19,0))
B25: APIM CONFIGURATION NOTES
B26: • Configure PTU endpoint as Priority 1 in APIM backend pool
B27: • Configure same-region PAYGO as Priority 2 (spillover)
B28: • Configure secondary region PAYGO as Priority 3 (DR)
B29: • Enable circuit breaker to auto-failover on 429 errors
B30: • Set retry policy with exponential backoff

Sheet Reservation Optimizer
B2: Reservation Optimizer
B3: Compare commitment terms and payment options
B5: RESERVATION COMPARISON
B6: Option | C6: Monthly Cost | D6: Annual Cost | E6: 3-Year Total | F6: Savings vs Hourly
B7: Hourly (No Commitment) | C7: ='Cost Analysis'!D8 | D7: ='Cost Analysis'!D9 | E7: ='Cost Analysis'!D9*3 | F7: 0
B8: 1-Year Reservation | C8: ='Cost Analysis'!D12 | D8: ='Cost Analysis'!D13 | E8: ='Cost Analysis'!D13*3 | F8: =E7-E8
B9: 3-Year Reservation | C9: ='Cost Analysis'!D15 | D9: ='Cost Analysis'!D16 | E9: ='Cost Analysis'!D16*3 | F9: =E7-E9
B12: BREAK-EVEN ANALYSIS
B13: 1-Year Break-Even (months) | C13: =IF(C7>C8,12/(1-C8/C7),"N/A")
B14: 3-Year Break-Even (months) | C14: =IF(C7>C9,36/(1-C9/C7),"N/A")
B17: RECOMMENDATION LOGIC
B18: • If workload duration < 6 months: Use hourly billing
B19: • If workload duration 6-18 months: Consider 1-year reservation
B20: • If workload duration > 18 months: 3-year reservation optimal
B21: • Always deploy first, then purchase reservation
B22: • Reservations can be exchanged (with fee) but not refunded

Sheet Chargeback Model
B2: Cost Allocation & Chargeback
B3: Allocate PTU costs to consuming applications/business units
B5: APPLICATION COST ALLOCATION
B6: Application | C6: TPM Share % | D6: PTU Allocation | E6: Monthly Cost | F6: Annual Cost | G6: Cost Center | H6: Owner
B7: ='Workload Inputs'!B8 | C7: =IFERROR('Workload Inputs'!E32/'Workload Inputs'!E53,0) | D7: =C7*'Capacity Summary'!D15 | E7: =D7*Configuration!C10*730 | F7: =E7*12
B8: ='Workload Inputs'!B9 | C8: =IFERROR('Workload Inputs'!E33/'Workload Inputs'!E53,0) | D8: =C8*'Capacity Summary'!D15 | E8: =D8*Configuration!C10*730 | F8: =E8*12
B9: ='Workload Inputs'!B10 | C9: =IFERROR('Workload Inputs'!E34/'Workload Inputs'!E53,0) | D9: =C9*'Capacity Summary'!D15 | E9: =D9*Configuration!C10*730 | F9: =E9*12
B10: ='Workload Inputs'!B11 | C10: =IFERROR('Workload Inputs'!E35/'Workload Inputs'!E53,0) | D10: =C10*'Capacity Summary'!D15 | E10: =D10*Configuration!C10*730 | F10: =E10*12
B11: ='Workload Inputs'!B12 | C11: =IFERROR('Workload Inputs'!E36/'Workload Inputs'!E53,0) | D11: =C11*'Capacity Summary'!D15 | E11: =D11*Configuration!C10*730 | F11: =E11*12
B12: ='Workload Inputs'!B13 | C12: =IFERROR('Workload Inputs'!E37/'Workload Inputs'!E53,0) | D12: =C12*'Capacity Summary'!D15 | E12: =D12*Configuration!C10*730 | F12: =E12*12
B13: ='Workload Inputs'!B14 | C13: =IFERROR('Workload Inputs'!E38/'Workload Inputs'!E53,0) | D13: =C13*'Capacity Summary'!D15 | E13: =D13*Configuration!C10*730 | F13: =E13*12
B14: ='Workload Inputs'!B15 | C14: =IFERROR('Workload Inputs'!E39/'Workload Inputs'!E53,0) | D14: =C14*'Capacity Summary'!D15 | E14: =D14*Configuration!C10*730 | F14: =E14*12
B15: ='Workload Inputs'!B16 | C15: =IFERROR('Workload Inputs'!E40/'Workload Inputs'!E53,0) | D15: =C15*'Capacity Summary'!D15 | E15: =D15*Configuration!C10*730 | F15: =E15*12
B16: ='Workload Inputs'!B17 | C16: =IFERROR('Workload Inputs'!E41/'Workload Inputs'!E53,0) | D16: =C16*'Capacity Summary'!D15 | E16: =D16*Configuration!C10*730 | F16: =E16*12
B18: TOTALS | C18: =SUM(C7:C16) | D18: =SUM(D7:D16) | E18: =SUM(E7:E16) | F18: =SUM(F7:F16)
B21: CHARGEBACK NOTES
B22: • Costs allocated proportionally based on TPM consumption
B23: • Update Cost Center and Owner fields for your organization
B24: • Export to finance systems via APIM subscription key metrics
B25: • Consider adding buffer allocation to shared/overhead cost center

Sheet Benchmarking Log
B2: Benchmarking & Validation Log
B3: Track benchmark tests to validate calculator estimates
B5: BENCHMARK RESULTS
B6: Date | C6: Application | D6: PTUs Tested | E6: Actual RPM | F6: P95 Latency (ms) | G6: Utilization % | H6: 429 Rate % | I6: Notes
B24: BENCHMARK GUIDANCE
B25: • Use Azure OpenAI Benchmark tool: github.com/Azure/azure-openai-benchmark
B26: • Test with representative prompts from actual application
B27: • Run tests for at least 10 minutes to reach stable state
B28: • Target 80-90% utilization without 429 errors
B29: • Record P95 latency - should meet SLA requirements
B30: • Update calculator inputs based on benchmark findings
